sharex/utils/__init__.py
sharex/utils/io.py
sharex-0.0.5.dist-info/METADATA
sharex-0.0.5.dist-info/WHEEL
sharex-0.0.5.dist-info/licenses/LICENSE
sharex-0.0.5.dist-info/RECORD
