Metadata-Version: 2.1
Name: sharex
Version: 0.0.5
Summary: A common sharex package
Project-URL: Homepage, https://github.com/KevinTao24/sharex
Project-URL: Bug Tracker, https://github.com/KevinTao24/sharex/issues
Author-email: Kevin Tao <minzetao@gmail.com>
License-File: LICENSE
Classifier: License :: OSI Approved :: MIT License
Classifier: Operating System :: OS Independent
Classifier: Programming Language :: Python :: 3
Requires-Python: >=3.8
